envpp/__init__.py
envpp/__main__.py
envpp/_api.py
envpp/_items.py
envpp/_items.py.template
envpp/_token.py
envpp/api.py
envpp/envpp.py
envpp_generator-1.0.1.dist-info/METADATA
envpp_generator-1.0.1.dist-info/WHEEL
envpp_generator-1.0.1.dist-info/RECORD
